awesome_pipeline/__init__.py
awesome_pipeline/de/__init__.py
awesome_pipeline/de/cerner_extract.py
awesome_pipeline/de/configuration.py
awesome_pipeline/de/data_load.py
awesome_pipeline/de/data_preparation.py
awesome_pipeline/de/data_quality_checker.py
awesome_pipeline/utils/__init__.py
awesome_pipeline/utils/db.py
awesome_pipeline/utils/de_utils.py
awesome_pipeline/utils/decorators.py
awesome_pipeline/utils/postgres_handler.py
awesome_pipeline/utils/test.py
data_pipeline/__init__.py
data_pipeline/de/__init__.py
data_pipeline/de/cerner_extract.py
data_pipeline/de/configuration.py
data_pipeline/de/data_load.py
data_pipeline/de/data_preparation.py
data_pipeline/de/data_quality_checker.py
data_pipeline/utils/__init__.py
data_pipeline/utils/db.py
data_pipeline/utils/de_utils.py
data_pipeline/utils/decorators.py
data_pipeline/utils/postgres_handler.py
data_pipeline/utils/test.py
de/__init__.py
de/configuration.py
de/data_preparation.py
utils/__init__.py
utils/db.py
utils/de_utils.py
utils/decorators.py
utils/ds_utils.py
utils/postgres_handler.py
utils/test.py
awesome_pipeline-0.0.9.dist-info/METADATA
awesome_pipeline-0.0.9.dist-info/WHEEL
awesome_pipeline-0.0.9.dist-info/top_level.txt
awesome_pipeline-0.0.9.dist-info/RECORD
