Metadata-Version: 2.4
Name: awesome_pipeline
Version: 0.0.9
Summary: A framework for data standardised pipeline  platform
Author: Andy Yang
Author-email: yong.yang@health.nsw.gov.au
License: private
Keywords: None
Requires-Python: >3.6
Requires-Dist: pandas
Requires-Dist: numpy
Requires-Dist: xmltodict
Requires-Dist: sqlalchemy
Requires-Dist: pyyaml
Requires-Dist: beautifulsoup4
Requires-Dist: pandasql
Requires-Dist: cryptography
Dynamic: author
Dynamic: author-email
Dynamic: description
Dynamic: keywords
Dynamic: license
Dynamic: requires-dist
Dynamic: requires-python
Dynamic: summary
